setup.cfg
setup.py
houdini_lexers/__init__.py
houdini_lexers/vex.py
houdini_lexers.egg-info/PKG-INFO
houdini_lexers.egg-info/SOURCES.txt
houdini_lexers.egg-info/dependency_links.txt
houdini_lexers.egg-info/entry_points.txt
houdini_lexers.egg-info/requires.txt
houdini_lexers.egg-info/top_level.txt