Metadata-Version: 1.1
Name: houdini-lexers
Version: 1.2
Summary: This package contains the pygments lexer for the vex language used in Houdini
Home-page: https://github.com/pirave/houdini-lexers
Author: SideFX Software Inc.
Author-email: pirave@sidefx.com
License: UNKNOWN
Download-URL: https://github.com/pirave/houdini-lexers/tarball/1.2
Platform: UNKNOWN
